scikit_build_example_ugrnn/_core.cpython-37m-i386-linux-gnu.so
scikit_build_example_ugrnn/__init__.py
scikit_build_example_ugrnn-0.0.1.dist-info/METADATA
scikit_build_example_ugrnn-0.0.1.dist-info/RECORD
scikit_build_example_ugrnn-0.0.1.dist-info/WHEEL
scikit_build_example_ugrnn-0.0.1.dist-info/licenses/LICENSE
